labeling_notebook_comic_ocr/__init__.py
labeling_notebook_comic_ocr-0.1.0.dist-info/LICENSE
labeling_notebook_comic_ocr-0.1.0.dist-info/WHEEL
labeling_notebook_comic_ocr-0.1.0.dist-info/METADATA
labeling_notebook_comic_ocr-0.1.0.dist-info/RECORD
