Metadata-Version: 2.1
Name: labeling-notebook-comic-ocr
Version: 0.1.0
Summary: The `labeling-notebook` plugin for applying `comic-ocr` models.
License: MIT
Author: Wanasit T
Requires-Python: >=3.8,<4.0
Classifier: License :: OSI Approved :: MIT License
Classifier: Programming Language :: Python :: 3
Classifier: Programming Language :: Python :: 3.10
Classifier: Programming Language :: Python :: 3.8
Classifier: Programming Language :: Python :: 3.9
Requires-Dist: comic-ocr (>=0.1.6,<0.2.0)
